MANIFEST.in
pyproject.toml
setup.cfg
src/ace_backend/__init__.py
src/ace_backend.egg-info/PKG-INFO
src/ace_backend.egg-info/SOURCES.txt
src/ace_backend.egg-info/dependency_links.txt
src/ace_backend.egg-info/entry_points.txt
src/ace_backend.egg-info/requires.txt
src/ace_backend.egg-info/top_level.txt
src/ace_backend/lib/__init__.py
src/ace_backend/lib/pg.py
src/ace_backend/lib/redis.py
src/ace_backend/lib/server.py
src/ace_backend/postgresql/pgmigrate/migrations/V01__initial_schema.sql
src/ace_backend/postgresql/pgmigrate/migrations/V02__messages.sql
src/ace_backend/postgresql/pgmigrate/migrations/V03__topic_touch.sql
src/ace_backend/server/__init__.py
src/ace_backend/server/main.py
src/ace_backend/server/handlers/__init__.py
src/ace_backend/server/handlers/v1_message_list_get.py
src/ace_backend/server/handlers/v1_message_post.py
src/ace_backend/server/handlers/v1_topic_get.py
src/ace_backend/server/handlers/v1_whoami_get.py
src/ace_backend/sync/__init__.py
src/ace_backend/sync/main.py
src/ace_backend/sync/message.py